module_bank/__init__.py
module_bank/cli.py
module_bank/python_to_sqlite.py
module_bank/sqlite_meta_path_finder.py
module_bank/sqlite_module_importer.py
module_bank/sqlite_module_loader.py
module_bank-0.1.1.dist-info/METADATA
module_bank-0.1.1.dist-info/WHEEL
module_bank-0.1.1.dist-info/entry_points.txt
module_bank-0.1.1.dist-info/licenses/LICENSE
module_bank-0.1.1.dist-info/RECORD
