Metadata-Version: 2.4
Name: module_bank
Version: 0.1.1
Summary: Add your description here
License-File: LICENSE
Requires-Python: >=3.7
